latencyscope/__init__.py
latencyscope/cli.py
latencyscope/output.py
latencyscope/profiler.py
latencyscope/py.typed
latencyscope/utils.py
latencyscope/modules/__init__.py
latencyscope/modules/irq.py
latencyscope/modules/isolation.py
latencyscope/modules/memory.py
latencyscope/modules/network.py
latencyscope/modules/syscall.py
latencyscope-0.1.1.dist-info/METADATA
latencyscope-0.1.1.dist-info/WHEEL
latencyscope-0.1.1.dist-info/entry_points.txt
latencyscope-0.1.1.dist-info/licenses/LICENSE
latencyscope-0.1.1.dist-info/RECORD
