Metadata-Version: 2.4
Name: latencyscope
Version: 0.1.1
Summary: HFT-grade latency profiler. eBPF-powered, nanosecond-accurate runtime tracing for trading infrastructure.
Project-URL: Homepage, https://nikhilpadala.com/latencyscope
Project-URL: Documentation, https://github.com/padalan/latencyscope#readme
Project-URL: Repository, https://github.com/padalan/latencyscope
Project-URL: Issues, https://github.com/padalan/latencyscope/issues
Project-URL: Changelog, https://github.com/padalan/latencyscope/blob/main/CHANGELOG.md
Author-email: Nikhil Padala <nikhil@nikhilpadala.com>
Maintainer-email: Nikhil Padala <nikhil@nikhilpadala.com>
License-Expression: MIT
License-File: LICENSE
Keywords: bpf,ebpf,hft,latency,linux,performance,profiler,tracing,trading
Classifier: Development Status :: 4 - Beta
Classifier: Environment :: Console
Classifier: Intended Audience :: Developers
Classifier: Intended Audience :: Financial and Insurance Industry
Classifier: Intended Audience :: System Administrators
Classifier: License :: OSI Approved :: MIT License
Classifier: Operating System :: POSIX :: Linux
Classifier: Programming Language :: Python :: 3
Classifier: Programming Language :: Python :: 3.10
Classifier: Programming Language :: Python :: 3.11
Classifier: Programming Language :: Python :: 3.12
Classifier: Programming Language :: Python :: 3.13
Classifier: Topic :: Software Development :: Debuggers
Classifier: Topic :: System :: Monitoring
Classifier: Topic :: System :: Systems Administration
Classifier: Typing :: Typed
Requires-Python: >=3.10
Requires-Dist: click>=8.1.0
Requires-Dist: hdrhistogram>=0.10.0
Requires-Dist: psutil>=5.9.0
Requires-Dist: rich>=13.0.0
Provides-Extra: dev
Requires-Dist: mypy>=1.8.0; extra == 'dev'
Requires-Dist: pre-commit>=3.6.0; extra == 'dev'
Requires-Dist: pytest-cov>=4.1.0; extra == 'dev'
Requires-Dist: pytest>=8.0.0; extra == 'dev'
Requires-Dist: ruff>=0.1.0; extra == 'dev'
